superluminar_io/super_eks/__init__.py
superluminar_io/super_eks/py.typed
superluminar_io/super_eks/_jsii/__init__.py
superluminar_io/super_eks/_jsii/super-eks@0.2.21.jsii.tgz
superluminar_io.super_eks-0.2.21.dist-info/LICENSE
superluminar_io.super_eks-0.2.21.dist-info/METADATA
superluminar_io.super_eks-0.2.21.dist-info/WHEEL
superluminar_io.super_eks-0.2.21.dist-info/top_level.txt
superluminar_io.super_eks-0.2.21.dist-info/RECORD
