Metadata-Version: 2.1
Name: superluminar-io.super-eks
Version: 0.2.21
Summary: super-eks is a CDK construct that provides a preconfigured EKS installation with batteries included.
Home-page: https://github.com/superluminar-io/super-eks.git
Author: superluminar
License: Apache-2.0
Project-URL: Source, https://github.com/superluminar-io/super-eks.git
Platform: UNKNOWN
Classifier: Intended Audience :: Developers
Classifier: Operating System :: OS Independent
Classifier: Programming Language :: JavaScript
Classifier: Programming Language :: Python :: 3 :: Only
Classifier: Programming Language :: Python :: 3.6
Classifier: Programming Language :: Python :: 3.7
Classifier: Programming Language :: Python :: 3.8
Classifier: Programming Language :: Python :: 3.9
Classifier: Typing :: Typed
Classifier: Development Status :: 5 - Production/Stable
Classifier: License :: OSI Approved
Requires-Python: >=3.6
License-File: LICENSE
Requires-Dist: aws-cdk-lib (<3.0.0,>=2.20.0)
Requires-Dist: constructs (<11.0.0,>=10.0.5)
Requires-Dist: jsii (<2.0.0,>=1.57.0)
Requires-Dist: publication (>=0.0.3)
